opytional/__init__.py
opytional/apply_if.py
opytional/apply_if_or_else.py
opytional/apply_if_or_value.py
opytional/or_else.py
opytional/or_value.py
opytional-0.1.0.dist-info/AUTHORS.rst
opytional-0.1.0.dist-info/LICENSE
opytional-0.1.0.dist-info/METADATA
opytional-0.1.0.dist-info/WHEEL
opytional-0.1.0.dist-info/top_level.txt
opytional-0.1.0.dist-info/RECORD
