Metadata-Version: 2.1
Name: opytional
Version: 0.1.0
Summary: opytional makes working with values that might be None safer and easier
Home-page: https://github.com/mmore500/opytional
Author: Matthew Andres Moreno
Author-email: m.more500@gmail.com
License: MIT license
Keywords: opytional
Platform: UNKNOWN
Classifier: Development Status :: 2 - Pre-Alpha
Classifier: Intended Audience :: Developers
Classifier: License :: OSI Approved :: MIT License
Classifier: Natural Language :: English
Classifier: Programming Language :: Python :: 3
Classifier: Programming Language :: Python :: 3.6
Classifier: Programming Language :: Python :: 3.7
Classifier: Programming Language :: Python :: 3.8
Requires-Python: >=3.6
